apt_pro/__init__.py
apt_pro/apt-pro.db
apt_pro/cli.py
apt_pro/main.py
apt_pro-1.1.2.dist-info/METADATA
apt_pro-1.1.2.dist-info/WHEEL
apt_pro-1.1.2.dist-info/entry_points.txt
apt_pro-1.1.2.dist-info/top_level.txt
apt_pro-1.1.2.dist-info/RECORD
