Metadata-Version: 2.1
Name: apt-pro
Version: 1.1.2
Summary: A python package for better update and manage your debian packages.
Home-page: https://github.com/jakbin/apt-pro
Author: Jak Bin
Project-URL: Bug Tracker, https://github.com/jakbin/apt-pro/issues
Keywords: python-apt,apt,package-manager,debian,apt-pro
Classifier: Programming Language :: Python :: 3
Classifier: License :: OSI Approved :: MIT License
Classifier: Operating System :: OS Independent
Requires-Python: >=3.6
Requires-Dist: rich
